regularized_var/__init__.py
regularized_var/metrics.py
regularized_var/model_selection.py
regularized_var/utils.py
regularized_var/var.py
regularized_var-0.1.1.dist-info/METADATA
regularized_var-0.1.1.dist-info/WHEEL
regularized_var-0.1.1.dist-info/licenses/LICENSE
regularized_var-0.1.1.dist-info/RECORD
