Metadata-Version: 2.4
Name: regularized-var
Version: 0.1.1
Summary: Regularized Vector Autoregression (VAR) with ridge shrinkage, Minnesota prior, metrics, and walk-forward validation.
Project-URL: Homepage, https://github.com/RachelDoehr/regularized-var
Project-URL: Issues, https://github.com/RachelDoehr/regularized-var/issues
Author: Rachel Doehr
License: The MIT License (MIT)
License-File: LICENSE
Keywords: VAR,econometrics,forecasting,ridge,time series
Classifier: Intended Audience :: Science/Research
Classifier: License :: OSI Approved :: MIT License
Classifier: Operating System :: OS Independent
Classifier: Programming Language :: Python :: 3
Classifier: Topic :: Scientific/Engineering :: Information Analysis
Classifier: Topic :: Scientific/Engineering :: Mathematics
Requires-Python: >=3.8
Requires-Dist: numpy>=1.22
Requires-Dist: pandas>=1.4
Requires-Dist: tqdm>=4.60
Provides-Extra: dev
Requires-Dist: black>=24.0; extra == 'dev'
Requires-Dist: mypy>=1.8; extra == 'dev'
Requires-Dist: pytest-cov>=4; extra == 'dev'
Requires-Dist: pytest>=7; extra == 'dev'
Requires-Dist: ruff>=0.5; extra == 'dev'
